stsci/__init__.py
stsci/skypac/__init__.py
stsci/skypac/hstinfo.py
stsci/skypac/pamutils.py
stsci/skypac/parseat.py
stsci/skypac/region.py
stsci/skypac/skyline.py
stsci/skypac/skymatch.help
stsci/skypac/skymatch.py
stsci/skypac/skystatistics.py
stsci/skypac/utils.py
stsci/skypac/version.py
stsci/skypac/pars/skymatch.cfg
stsci/skypac/pars/skymatch.cfgspc
stsci_skypac-1.0.11.dist-info/licenses/LICENSE.txt
stsci_skypac-1.0.11.dist-info/METADATA
stsci_skypac-1.0.11.dist-info/WHEEL
stsci_skypac-1.0.11.dist-info/top_level.txt
stsci_skypac-1.0.11.dist-info/RECORD
