Metadata-Version: 2.4
Name: stsci.skypac
Version: 1.0.11
Summary: Sky matching on image mosaic
Author: Warren Hack, Pey Lian Lim
Author-email: Mihai Cara <help@stsci.edu>
Project-URL: repository, https://github.com/spacetelescope/stsci.skypac
Project-URL: Bug Reports, https://github.com/spacetelescope/stsci.skypac/issues/
Project-URL: Source, https://github.com/spacetelescope/stsci.skypac/
Project-URL: Help, https://hsthelp.stsci.edu/
Classifier: Intended Audience :: Science/Research
Classifier: Operating System :: OS Independent
Classifier: Programming Language :: Python :: 3
Classifier: Topic :: Scientific/Engineering :: Astronomy
Classifier: Topic :: Scientific/Engineering :: Physics
Classifier: Development Status :: 7 - Inactive
Requires-Python: >=3.10
License-File: LICENSE.txt
Requires-Dist: astropy>=5.0.4
Requires-Dist: numpy
Requires-Dist: spherical_geometry>=1.2.2
Requires-Dist: stsci.imagestats
Requires-Dist: stsci.tools
Requires-Dist: stwcs
Requires-Dist: packaging>=21.1
Provides-Extra: test
Requires-Dist: pytest; extra == "test"
Requires-Dist: pytest-cov; extra == "test"
Requires-Dist: pytest-doctestplus; extra == "test"
Provides-Extra: docs
Requires-Dist: numpydoc; extra == "docs"
Requires-Dist: graphviz; extra == "docs"
Requires-Dist: sphinx; extra == "docs"
Requires-Dist: sphinx_rtd_theme; extra == "docs"
Requires-Dist: sphinx_automodapi; extra == "docs"
Dynamic: license-file
